setup.py
test_distributions3/Binomialdistribution.py
test_distributions3/Gaussiandistribution.py
test_distributions3/Generaldistribution.py
test_distributions3/__init__.py
test_distributions3.egg-info/PKG-INFO
test_distributions3.egg-info/SOURCES.txt
test_distributions3.egg-info/dependency_links.txt
test_distributions3.egg-info/not-zip-safe
test_distributions3.egg-info/top_level.txt